bootstrap.py
main.py
command/__init__.py
command/hello.py
php/__init__.py
php/composer.py
php/libmap.py
php/main.py
util/__init__.py
util/output.py
util/urlhelper.py
feb-0.1.dist-info/METADATA
feb-0.1.dist-info/WHEEL
feb-0.1.dist-info/entry_points.txt
feb-0.1.dist-info/top_level.txt
feb-0.1.dist-info/RECORD
